{"nodes": [{"id": "apps_server_internal_infra_cache_redis_go", "label": "redis.go", "file_type": "code", "source_file": "apps/server/internal/infra/cache/redis.go", "source_location": "L1"}, {"id": "cache_rediscache", "label": "RedisCache", "file_type": "code", "source_file": "apps/server/internal/infra/cache/redis.go", "source_location": "L14"}, {"id": "redis_newredis", "label": "NewRedis()", "file_type": "code", "source_file": "apps/server/internal/infra/cache/redis.go", "source_location": "L19"}, {"id": "cache_rediscache_client", "label": ".Client()", "file_type": "code", "source_file": "apps/server/internal/infra/cache/redis.go", "source_location": "L43"}, {"id": "cache_rediscache_get", "label": ".Get()", "file_type": "code", "source_file": "apps/server/internal/infra/cache/redis.go", "source_location": "L47"}, {"id": "cache_rediscache_set", "label": ".Set()", "file_type": "code", "source_file": "apps/server/internal/infra/cache/redis.go", "source_location": "L58"}, {"id": "cache_rediscache_del", "label": ".Del()", "file_type": "code", "source_file": "apps/server/internal/infra/cache/redis.go", "source_location": "L65"}, {"id": "cache_rediscache_exists", "label": ".Exists()", "file_type": "code", "source_file": "apps/server/internal/infra/cache/redis.go", "source_location": "L72"}, {"id": "cache_rediscache_ping", "label": ".Ping()", "file_type": "code", "source_file": "apps/server/internal/infra/cache/redis.go", "source_location": "L80"}, {"id": "cache_rediscache_close", "label": ".Close()", "file_type": "code", "source_file": "apps/server/internal/infra/cache/redis.go", "source_location": "L84"}], "edges": [{"source": "apps_server_internal_infra_cache_redis_go", "target": "context", "relation": "imports_from", "confidence": "EXTRACTED", "source_file": "apps/server/internal/infra/cache/redis.go", "source_location": "L4", "weight": 1.0}, {"source": "apps_server_internal_infra_cache_redis_go", "target": "fmt", "relation": "imports_from", "confidence": "EXTRACTED", "source_file": "apps/server/internal/infra/cache/redis.go", "source_location": "L5", "weight": 1.0}, {"source": "apps_server_internal_infra_cache_redis_go", "target": "time", "relation": "imports_from", "confidence": "EXTRACTED", "source_file": "apps/server/internal/infra/cache/redis.go", "source_location": "L6", "weight": 1.0}, {"source": "apps_server_internal_infra_cache_redis_go", "target": "v9", "relation": "imports_from", "confidence": "EXTRACTED", "source_file": "apps/server/internal/infra/cache/redis.go", "source_location": "L8", "weight": 1.0}, {"source": "apps_server_internal_infra_cache_redis_go", "target": "cache_rediscache", "relation": "contains", "confidence": "EXTRACTED", "source_file": "apps/server/internal/infra/cache/redis.go", "source_location": "L14", "weight": 1.0}, {"source": "apps_server_internal_infra_cache_redis_go", "target": "redis_newredis", "relation": "contains", "confidence": "EXTRACTED", "source_file": "apps/server/internal/infra/cache/redis.go", "source_location": "L19", "weight": 1.0}, {"source": "cache_rediscache", "target": "cache_rediscache_client", "relation": "method", "confidence": "EXTRACTED", "source_file": "apps/server/internal/infra/cache/redis.go", "source_location": "L43", "weight": 1.0}, {"source": "cache_rediscache", "target": "cache_rediscache_get", "relation": "method", "confidence": "EXTRACTED", "source_file": "apps/server/internal/infra/cache/redis.go", "source_location": "L47", "weight": 1.0}, {"source": "cache_rediscache", "target": "cache_rediscache_set", "relation": "method", "confidence": "EXTRACTED", "source_file": "apps/server/internal/infra/cache/redis.go", "source_location": "L58", "weight": 1.0}, {"source": "cache_rediscache", "target": "cache_rediscache_del", "relation": "method", "confidence": "EXTRACTED", "source_file": "apps/server/internal/infra/cache/redis.go", "source_location": "L65", "weight": 1.0}, {"source": "cache_rediscache", "target": "cache_rediscache_exists", "relation": "method", "confidence": "EXTRACTED", "source_file": "apps/server/internal/infra/cache/redis.go", "source_location": "L72", "weight": 1.0}, {"source": "cache_rediscache", "target": "cache_rediscache_ping", "relation": "method", "confidence": "EXTRACTED", "source_file": "apps/server/internal/infra/cache/redis.go", "source_location": "L80", "weight": 1.0}, {"source": "cache_rediscache", "target": "cache_rediscache_close", "relation": "method", "confidence": "EXTRACTED", "source_file": "apps/server/internal/infra/cache/redis.go", "source_location": "L84", "weight": 1.0}, {"source": "redis_newredis", "target": "cache_rediscache_ping", "relation": "calls", "confidence": "EXTRACTED", "source_file": "apps/server/internal/infra/cache/redis.go", "source_location": "L34", "weight": 1.0}, {"source": "redis_newredis", "target": "cache_rediscache_close", "relation": "calls", "confidence": "EXTRACTED", "source_file": "apps/server/internal/infra/cache/redis.go", "source_location": "L35", "weight": 1.0}], "raw_calls": [{"caller_nid": "redis_newredis", "callee": "Errorf", "source_file": "apps/server/internal/infra/cache/redis.go", "source_location": "L21"}, {"caller_nid": "redis_newredis", "callee": "ParseURL", "source_file": "apps/server/internal/infra/cache/redis.go", "source_location": "L24"}, {"caller_nid": "redis_newredis", "callee": "Errorf", "source_file": "apps/server/internal/infra/cache/redis.go", "source_location": "L26"}, {"caller_nid": "redis_newredis", "callee": "NewClient", "source_file": "apps/server/internal/infra/cache/redis.go", "source_location": "L29"}, {"caller_nid": "redis_newredis", "callee": "WithTimeout", "source_file": "apps/server/internal/infra/cache/redis.go", "source_location": "L31"}, {"caller_nid": "redis_newredis", "callee": "Background", "source_file": "apps/server/internal/infra/cache/redis.go", "source_location": "L31"}, {"caller_nid": "redis_newredis", "callee": "cancel", "source_file": "apps/server/internal/infra/cache/redis.go", "source_location": "L32"}, {"caller_nid": "redis_newredis", "callee": "Err", "source_file": "apps/server/internal/infra/cache/redis.go", "source_location": "L34"}, {"caller_nid": "redis_newredis", "callee": "Errorf", "source_file": "apps/server/internal/infra/cache/redis.go", "source_location": "L36"}, {"caller_nid": "cache_rediscache_get", "callee": "Bytes", "source_file": "apps/server/internal/infra/cache/redis.go", "source_location": "L48"}, {"caller_nid": "cache_rediscache_get", "callee": "Get", "source_file": "apps/server/internal/infra/cache/redis.go", "source_location": "L48"}, {"caller_nid": "cache_rediscache_get", "callee": "Errorf", "source_file": "apps/server/internal/infra/cache/redis.go", "source_location": "L53"}, {"caller_nid": "cache_rediscache_set", "callee": "Err", "source_file": "apps/server/internal/infra/cache/redis.go", "source_location": "L59"}, {"caller_nid": "cache_rediscache_set", "callee": "Set", "source_file": "apps/server/internal/infra/cache/redis.go", "source_location": "L59"}, {"caller_nid": "cache_rediscache_set", "callee": "Errorf", "source_file": "apps/server/internal/infra/cache/redis.go", "source_location": "L60"}, {"caller_nid": "cache_rediscache_del", "callee": "Err", "source_file": "apps/server/internal/infra/cache/redis.go", "source_location": "L66"}, {"caller_nid": "cache_rediscache_del", "callee": "Del", "source_file": "apps/server/internal/infra/cache/redis.go", "source_location": "L66"}, {"caller_nid": "cache_rediscache_del", "callee": "Errorf", "source_file": "apps/server/internal/infra/cache/redis.go", "source_location": "L67"}, {"caller_nid": "cache_rediscache_exists", "callee": "Result", "source_file": "apps/server/internal/infra/cache/redis.go", "source_location": "L73"}, {"caller_nid": "cache_rediscache_exists", "callee": "Exists", "source_file": "apps/server/internal/infra/cache/redis.go", "source_location": "L73"}, {"caller_nid": "cache_rediscache_exists", "callee": "Errorf", "source_file": "apps/server/internal/infra/cache/redis.go", "source_location": "L75"}, {"caller_nid": "cache_rediscache_ping", "callee": "Err", "source_file": "apps/server/internal/infra/cache/redis.go", "source_location": "L81"}, {"caller_nid": "cache_rediscache_ping", "callee": "Ping", "source_file": "apps/server/internal/infra/cache/redis.go", "source_location": "L81"}, {"caller_nid": "cache_rediscache_close", "callee": "Close", "source_file": "apps/server/internal/infra/cache/redis.go", "source_location": "L85"}]}